sharkiqpy/__init__.py
sharkiqpy/ayla_api.py
sharkiqpy/const.py
sharkiqpy/exc.py
sharkiqpy/sharkiq.py
sharkiqpy-0.1.9.dist-info/METADATA
sharkiqpy-0.1.9.dist-info/WHEEL
sharkiqpy-0.1.9.dist-info/top_level.txt
sharkiqpy-0.1.9.dist-info/RECORD
