Metadata-Version: 2.1
Name: sharkiqpy
Version: 0.1.9
Summary: Python API for Shark IQ robots
Home-page: https://github.com/ajmarks/sharkiq
Author: Andrew Marks
Author-email: ajmarks@gmail.com
License: MIT
Platform: UNKNOWN
Classifier: License :: OSI Approved :: MIT License
Classifier: Programming Language :: Python :: 3
Classifier: Programming Language :: Python :: 3.7
Requires-Dist: aiohttp
Requires-Dist: requests
